Tools.py
delipack/Tool.py
delipack/__init__.py
updelipack-1.0.0.dist-info/LICENSE.txt
updelipack-1.0.0.dist-info/METADATA
updelipack-1.0.0.dist-info/WHEEL
updelipack-1.0.0.dist-info/top_level.txt
updelipack-1.0.0.dist-info/RECORD
