Metadata-Version: 2.1
Name: updelipack
Version: 1.0.0
Summary: delipak file is my files of first
Home-page: UNKNOWN
Author: ZC
Author-email: 598714971@qq.com
License: MIT License
Platform: UNKNOWN
